call_args/__init__.py
call_args/call_args.py
call_args/func.py
call_args/py.typed
call_args/version.py
call_args-1.0.0.dist-info/METADATA
call_args-1.0.0.dist-info/WHEEL
call_args-1.0.0.dist-info/RECORD
