Metadata-Version: 2.1
Name: call-args
Version: 1.0.0
Summary: Call functions and create objects by easily assigning values of keyword arguments from some object's attributes of or items from some dictionary.
Project-URL: Homepage, https://github.com/vsego/call-args
Project-URL: Bug Tracker, https://github.com/vsego/call-args/issues
Project-URL: Changelog, https://github.com/vsego/call-args/blob/master/CHANGELOG.md
Author-email: Vedran Sego <vsego@vsego.org>
License-Expression: MIT
Classifier: Operating System :: OS Independent
Classifier: Programming Language :: Python :: 3.10
Classifier: Programming Language :: Python :: 3.11
Classifier: Typing :: Typed
Requires-Python: >=3.10
